LICENSE
MANIFEST.in
README.rst
setup.py
epoch_analyzer/__init__.py
epoch_analyzer/date_time.py
epoch_analyzer/date_time_bitpacked.py
epoch_analyzer/date_time_composition.py
epoch_analyzer/epoch_console.py
epoch_analyzer/epoch_search_console.py
epoch_analyzer.egg-info/PKG-INFO
epoch_analyzer.egg-info/SOURCES.txt
epoch_analyzer.egg-info/dependency_links.txt
epoch_analyzer.egg-info/entry_points.txt
epoch_analyzer.egg-info/top_level.txt
epoch_analyzer/epoch/__init__.py
epoch_analyzer/epoch/epoch.py
epoch_analyzer/unit/__init__.py
epoch_analyzer/unit/unit.py