Metadata-Version: 1.1
Name: epoch-analyzer
Version: 0.4
Summary: Utility detect probable date/time formats given a numeric input.
Home-page: https://github.com/martinvw/epoch-analyzer
Author: Martin van Wingerden
Author-email: martinvw@mtin.nl
License: MIT
Download-URL: https://github.com/martinvw/epoch-analyzer/tarball/v0.4
Keywords: datetime,timestamp,epoch
Platform: UNKNOWN
Classifier: Environment :: Console
Classifier: Intended Audience :: Developers
Classifier: Intended Audience :: System Administrators
Classifier: License :: OSI Approved :: MIT License
Classifier: Operating System :: POSIX :: Linux
Classifier: Programming Language :: Python :: 3.2
Classifier: Programming Language :: Python :: 3.3
Classifier: Programming Language :: Python :: 3.4
Classifier: Programming Language :: Python :: 3.5
Classifier: Topic :: Scientific/Engineering :: Information Analysis
Classifier: Topic :: System :: Filesystems
Classifier: Development Status :: 4 - Beta
Classifier: Topic :: Terminals
Classifier: Topic :: Utilities
